MANIFEST.in
README.rst
multitail.py
setup.py
multitail.egg-info/PKG-INFO
multitail.egg-info/SOURCES.txt
multitail.egg-info/dependency_links.txt
multitail.egg-info/top_level.txt