Metadata-Version: 1.0
Name: multitail
Version: 1.2
Summary: Python generator which implements `tail -f`-like behaviour, with support for tailing multiple files.
Home-page: https://bitbucket.org/rushman/multitail
Author: Sergey Kirilov
Author-email: sergey.kirillov@gmail.com
License: Apache License 2.0
Keywords: tail
Platform: UNKNOWN
